ogwallet_ct_lib/__init__.py
ogwallet_ct_lib/og_wallet.py
ogwallet_ct_lib-0.2.0.dist-info/METADATA
ogwallet_ct_lib-0.2.0.dist-info/WHEEL
ogwallet_ct_lib-0.2.0.dist-info/RECORD
