Metadata-Version: 2.1
Name: ogwallet-ct-lib
Version: 0.2.0
Summary: 
Author: Angel R. L.
Author-email: angel.delriolobato@onchainlabs.ch
Requires-Python: >=3.11,<4.0
Classifier: Programming Language :: Python :: 3
Classifier: Programming Language :: Python :: 3.11
Classifier: Programming Language :: Python :: 3.12
Requires-Dist: requests (>=2.32.3,<3.0.0)
